anylog_node/api/__init__.cpython-310-darwin.so
anylog_node/api/__init__.py
anylog_node/api/al_grafana.cpython-310-darwin.so
anylog_node/api/al_grafana.py
anylog_node/api/al_kafka.cpython-310-darwin.so
anylog_node/api/al_kafka.py
anylog_node/blockchain/__init__.cpython-310-darwin.so
anylog_node/blockchain/__init__.py
anylog_node/blockchain/al_auth.cpython-310-darwin.so
anylog_node/blockchain/al_auth.py
anylog_node/blockchain/blockchain.cpython-310-darwin.so
anylog_node/blockchain/blockchain.py
anylog_node/blockchain/bplatform.cpython-310-darwin.so
anylog_node/blockchain/bplatform.py
anylog_node/blockchain/bsync.cpython-310-darwin.so
anylog_node/blockchain/bsync.py
anylog_node/blockchain/eos.cpython-310-darwin.so
anylog_node/blockchain/eos.py
anylog_node/blockchain/ethereum.cpython-310-darwin.so
anylog_node/blockchain/ethereum.py
anylog_node/blockchain/gateway.cpython-310-darwin.so
anylog_node/blockchain/gateway.py
anylog_node/blockchain/hyperledger.cpython-310-darwin.so
anylog_node/blockchain/hyperledger.py
anylog_node/blockchain/metadata.cpython-310-darwin.so
anylog_node/blockchain/metadata.py
anylog_node/cmd/__init__.cpython-310-darwin.so
anylog_node/cmd/__init__.py
anylog_node/cmd/data_monitor.cpython-310-darwin.so
anylog_node/cmd/data_monitor.py
anylog_node/cmd/json_instruct.cpython-310-darwin.so
anylog_node/cmd/json_instruct.py
anylog_node/cmd/member_cmd.cpython-310-darwin.so
anylog_node/cmd/member_cmd.py
anylog_node/cmd/monitor.cpython-310-darwin.so
anylog_node/cmd/monitor.py
anylog_node/cmd/native_api.cpython-310-darwin.so
anylog_node/cmd/native_api.py
anylog_node/cmd/permissions.cpython-310-darwin.so
anylog_node/cmd/permissions.py
anylog_node/cmd/user_cmd.cpython-310-darwin.so
anylog_node/cmd/user_cmd.py
anylog_node/dbms/__init__.cpython-310-darwin.so
anylog_node/dbms/__init__.py
anylog_node/dbms/create_table.cpython-310-darwin.so
anylog_node/dbms/create_table.py
anylog_node/dbms/cursor_info.cpython-310-darwin.so
anylog_node/dbms/cursor_info.py
anylog_network-0.0.6.dist-info/METADATA
anylog_network-0.0.6.dist-info/WHEEL
anylog_network-0.0.6.dist-info/top_level.txt
anylog_network-0.0.6.dist-info/RECORD
