Metadata-Version: 2.1
Name: anylog-network
Version: 0.0.6
Summary: Copywrite AnyLog Co.
Home-page: https://anylog.co
Author: AnyLog Co.
Author-email: info@anylog.co
License: Copywrite AnyLog Co.
